soup.py
ipython_beautifulsoup-0.3.dist-info/metadata.json
ipython_beautifulsoup-0.3.dist-info/top_level.txt
ipython_beautifulsoup-0.3.dist-info/RECORD
ipython_beautifulsoup-0.3.dist-info/WHEEL
ipython_beautifulsoup-0.3.dist-info/DESCRIPTION.rst
ipython_beautifulsoup-0.3.dist-info/METADATA
