Metadata-Version: 1.1
Name: ipython-beautifulsoup
Version: 0.3
Summary: Custom rendering of beautifulsoup objects       in IPython notebook and qtconsole
Home-page: https://github.com/Psycojoker/ipython-beautifulsoup
Author: Laurent Peuch
Author-email: cortex@worlddomination.be
License: MIT
Keywords: ipython beautifulsoup parsing scraping
Platform: UNKNOWN
Classifier: Development Status :: 4 - Beta
Classifier: Intended Audience :: Developers
Classifier: License :: OSI Approved :: MIT License
Classifier: Framework :: IPython
Classifier: Programming Language :: Python :: 2.7
Classifier: Programming Language :: Python :: 3.3
Classifier: Programming Language :: Python :: 3.4
Classifier: Topic :: Text Processing :: Markup :: HTML
Classifier: Topic :: Text Processing :: Markup :: XML
Classifier: Topic :: Text Processing :: Markup :: SGML
Classifier: Topic :: Software Development :: Libraries :: Python Modules
